msqms/__init__.py
msqms/_version.py
msqms/constants.py
msqms/cli/__init__.py
msqms/cli/workflow.py
msqms/conf/config.yaml
msqms/conf/opm/quality_config.yaml
msqms/conf/squid/quality_config.yaml
msqms/io/__init__.py
msqms/io/bids_dataset.py
msqms/io/raw_dataset.py
msqms/libs/__init__.py
msqms/libs/osl/__init__.py
msqms/libs/osl/osl_wrappers.py
msqms/libs/pyprep/__init__.py
msqms/libs/pyprep/_version.py
msqms/libs/pyprep/find_noisy_channels.py
msqms/libs/pyprep/prep_pipeline.py
msqms/libs/pyprep/ransac.py
msqms/libs/pyprep/reference.py
msqms/libs/pyprep/removeTrend.py
msqms/libs/pyprep/utils.py
msqms/qc/__init__.py
msqms/qc/basic_info.py
msqms/qc/entropy_metrics.py
msqms/qc/fractal_metrics.py
msqms/qc/freq_domain_metrics.py
msqms/qc/metrics.py
msqms/qc/metrics_factory.py
msqms/qc/msqm.py
msqms/qc/statistic_metrics.py
msqms/qc/time_domain_metrcis.py
msqms/qc/visual_inspection.py
msqms/quality_reference/__init__.py
msqms/quality_reference/format_yaml.py
msqms/quality_reference/opm_quality_reference.yaml
msqms/quality_reference/quality_reference.py
msqms/quality_reference/squid_quality_reference.yaml
msqms/reports/__init__.py
msqms/reports/report.py
msqms/reports/templates/base.html
msqms/reports/templates/footer.html
msqms/reports/templates/javascript.html
msqms/reports/templates/navigation.html
msqms/reports/templates/panel_artifacts.html
msqms/reports/templates/panel_ica.html
msqms/reports/templates/panel_info.html
msqms/reports/templates/panel_inspection.html
msqms/reports/templates/panel_overview.html
msqms/reports/templates/style.html
msqms/reports/templates/css/bootstrap-iso-4.3.1.min.css
msqms/reports/templates/css/custom_quality_report.css
msqms/reports/templates/css/style.css
msqms/reports/templates/js/bootstrap-4.3.1.min.js
msqms/reports/templates/js/custom_script.js
msqms/reports/templates/js/jquery-2.1.1.min.js
msqms/tests/__init__.py
msqms/tests/test_data_path.py
msqms/utils/__init__.py
msqms/utils/logging.py
msqms/utils/natural_sort.py
msqms-0.1.1.dist-info/METADATA
msqms-0.1.1.dist-info/WHEEL
msqms-0.1.1.dist-info/entry_points.txt
msqms-0.1.1.dist-info/top_level.txt
msqms-0.1.1.dist-info/RECORD
