Metadata-Version: 2.4
Name: msqms
Version: 0.1.1
Summary: msqms is a fully automated quality control tool for OPM-MEG.
Home-page: https://github.com/liaopan/msqms
Download-URL: http://github.com/liaopan/msqms
Maintainer: reallo
Maintainer-email: liaopan_2015@163.com
License: MIT-License
Keywords: Neuroscience neuroimaging OPM-MEG and SQUID-MEG.
Classifier: Intended Audience :: Science/Research
Classifier: Intended Audience :: Developers
Classifier: License :: OSI Approved
Classifier: Programming Language :: Python
Classifier: Topic :: Software Development
Classifier: Topic :: Scientific/Engineering
Classifier: Operating System :: Microsoft :: Windows
Classifier: Operating System :: POSIX
Classifier: Operating System :: Unix
Classifier: Operating System :: MacOS
Classifier: Programming Language :: Python :: 3
Requires-Python: >=3.8
Requires-Dist: dill==0.3.8
Requires-Dist: hydra-core==1.3.2
Requires-Dist: Jinja2>=3.1.3
Requires-Dist: joblib==1.3.2
Requires-Dist: minify_html==0.15.0
Requires-Dist: mne>=1.5.0
Requires-Dist: mne_bids==0.14
Requires-Dist: numba==0.59.1
Requires-Dist: omegaconf==2.3.0
Requires-Dist: pandas==2.2.2
Requires-Dist: pytest==8.2.0
Requires-Dist: scipy==1.13.0
Requires-Dist: tqdm==4.66.2
Requires-Dist: loguru==0.7.2
Requires-Dist: python-box==7.1.1
Requires-Dist: seaborn==0.13.2
Requires-Dist: plotly==5.22.0
Requires-Dist: antropy==0.1.6
Requires-Dist: PyWavelets==1.6.0
Requires-Dist: tsfresh==0.20.0
Requires-Dist: fire==0.6.0
Requires-Dist: psutil==5.9.8
Requires-Dist: Deprecated>=1.2.14
Dynamic: classifier
Dynamic: description
Dynamic: description-content-type
Dynamic: download-url
Dynamic: home-page
Dynamic: keywords
Dynamic: license
Dynamic: maintainer
Dynamic: maintainer-email
Dynamic: requires-dist
Dynamic: requires-python
Dynamic: summary
